Workbook
Name Slicer_Region: #N/A

Sheet Dashboard
A1: Retail Sales & Customer Experience Dashboard
A11: Months | B11: Sales | C11: Profit | D11: Orders | F11: Region | G11: Sales | H11: Profit | I11: Return Rate
A12: ='Monthly Sales and Profit Trend'!G27 -> Jan 2025 | B12: ='Monthly Sales and Profit Trend'!H27 -> 605987.07 | C12: ='Monthly Sales and Profit Trend'!I27 -> 99784.884 | D12: ='Monthly Sales and Profit Trend'!J27 -> 30 | F12: ='Sales and Profit by Region'!A4 -> East | G12: ='Sales and Profit by Region'!B4 -> 2607497.1 | H12: ='Sales and Profit by Region'!C4 -> 418844.15 | I12: =COUNTIFS(Sales_Data!$G$2:$G$501,$F12,Sales_Data!$T$2:$T$501,"Yes")/COUNTIF(Sales_Data!$G$2:$G$501,$F12) -> 0.036764706
A13: ='Monthly Sales and Profit Trend'!G28 -> Feb 2025 | B13: ='Monthly Sales and Profit Trend'!H28 -> 489588.35 | C13: ='Monthly Sales and Profit Trend'!I28 -> 80249.472 | D13: ='Monthly Sales and Profit Trend'!J28 -> 41 | F13: ='Sales and Profit by Region'!A5 -> North | G13: ='Sales and Profit by Region'!B5 -> 2084247.9 | H13: ='Sales and Profit by Region'!C5 -> 367803.04 | I13: =COUNTIFS(Sales_Data!$G$2:$G$501,$F13,Sales_Data!$T$2:$T$501,"Yes")/COUNTIF(Sales_Data!$G$2:$G$501,$F13) -> 0.053097345
A14: ='Monthly Sales and Profit Trend'!G29 -> Mar 2025 | B14: ='Monthly Sales and Profit Trend'!H29 -> 1218851.5 | C14: ='Monthly Sales and Profit Trend'!I29 -> 198394.17 | D14: ='Monthly Sales and Profit Trend'!J29 -> 47 | F14: ='Sales and Profit by Region'!A6 -> South | G14: ='Sales and Profit by Region'!B6 -> 2268019.2 | H14: ='Sales and Profit by Region'!C6 -> 363838.19 | I14: =COUNTIFS(Sales_Data!$G$2:$G$501,$F14,Sales_Data!$T$2:$T$501,"Yes")/COUNTIF(Sales_Data!$G$2:$G$501,$F14) -> 0.045454545
A15: ='Monthly Sales and Profit Trend'!G30 -> Apr 2025 | B15: ='Monthly Sales and Profit Trend'!H30 -> 959716.7 | C15: ='Monthly Sales and Profit Trend'!I30 -> 154358.76 | D15: ='Monthly Sales and Profit Trend'!J30 -> 45 | F15: ='Sales and Profit by Region'!A7 -> West | G15: ='Sales and Profit by Region'!B7 -> 2154382.4 | H15: ='Sales and Profit by Region'!C7 -> 345951.84 | I15: =COUNTIFS(Sales_Data!$G$2:$G$501,$F15,Sales_Data!$T$2:$T$501,"Yes")/COUNTIF(Sales_Data!$G$2:$G$501,$F15) -> 0.050420168
A16: ='Monthly Sales and Profit Trend'!G31 -> May 2025 | B16: ='Monthly Sales and Profit Trend'!H31 -> 347485.69 | C16: ='Monthly Sales and Profit Trend'!I31 -> 51466.189 | D16: ='Monthly Sales and Profit Trend'!J31 -> 44
A17: ='Monthly Sales and Profit Trend'!G32 -> Jun 2025 | B17: ='Monthly Sales and Profit Trend'!H32 -> 1425448.7 | C17: ='Monthly Sales and Profit Trend'!I32 -> 245588.69 | D17: ='Monthly Sales and Profit Trend'!J32 -> 42
A18: ='Monthly Sales and Profit Trend'!G33 -> Jul 2025 | B18: ='Monthly Sales and Profit Trend'!H33 -> 390605.01 | C18: ='Monthly Sales and Profit Trend'!I33 -> 67516.88 | D18: ='Monthly Sales and Profit Trend'!J33 -> 32
A19: ='Monthly Sales and Profit Trend'!G34 -> Aug 2025 | B19: ='Monthly Sales and Profit Trend'!H34 -> 771290.9 | C19: ='Monthly Sales and Profit Trend'!I34 -> 124616.21 | D19: ='Monthly Sales and Profit Trend'!J34 -> 43 | F19: Category | G19: Sales | H19: Profit | I19: Avg Rating
A20: ='Monthly Sales and Profit Trend'!G35 -> Sep 2025 | B20: ='Monthly Sales and Profit Trend'!H35 -> 429680.15 | C20: ='Monthly Sales and Profit Trend'!I35 -> 75723.353 | D20: ='Monthly Sales and Profit Trend'!J35 -> 38 | F20: ='Sales and Profit by Category'!A28 -> Electronics | G20: ='Sales and Profit by Category'!B28 -> 5732221.2 | H20: ='Sales and Profit by Category'!C28 -> 852895.48 | I20: ='Sales and Profit by Category'!D28 -> 4.2988095
A21: ='Monthly Sales and Profit Trend'!G36 -> Oct 2025 | B21: ='Monthly Sales and Profit Trend'!H36 -> 623210.09 | C21: ='Monthly Sales and Profit Trend'!I36 -> 99176.011 | D21: ='Monthly Sales and Profit Trend'!J36 -> 44 | F21: ='Sales and Profit by Category'!A29 -> Furniture | G21: ='Sales and Profit by Category'!B29 -> 2440570.9 | H21: ='Sales and Profit by Category'!C29 -> 498103.66 | I21: ='Sales and Profit by Category'!D29 -> 4.2931373
A22: ='Monthly Sales and Profit Trend'!G37 -> Nov 2025 | B22: ='Monthly Sales and Profit Trend'!H37 -> 936248.44 | C22: ='Monthly Sales and Profit Trend'!I37 -> 139943.52 | D22: ='Monthly Sales and Profit Trend'!J37 -> 42 | F22: ='Sales and Profit by Category'!A30 -> Home & Lifestyle | G22: ='Sales and Profit by Category'!B30 -> 815273.69 | H22: ='Sales and Profit by Category'!C30 -> 163090.55 | I22: ='Sales and Profit by Category'!D30 -> 4.2807229
A23: ='Monthly Sales and Profit Trend'!G38 -> Dec 2025 | B23: ='Monthly Sales and Profit Trend'!H38 -> 916034.02 | C23: ='Monthly Sales and Profit Trend'!I38 -> 159619.08 | D23: ='Monthly Sales and Profit Trend'!J38 -> 52 | F23: ='Sales and Profit by Category'!A31 -> Office Supplies | G23: ='Sales and Profit by Category'!B31 -> 126080.77 | H23: ='Sales and Profit by Category'!C31 -> -17652.46 | I23: ='Sales and Profit by Category'!D31 -> 4.2061224

Sheet Analysis
A1: Retail Sales & Customer Experience Dashboard Analysis
A3: Business question | B3: Insight | C3: Implication | D3: Suggested action
A4: How is the business performing overall? | B4: Performance is strong but uneven across categories, regions, and months | C4: Revenue and profit are led by Electronics and the East region, while Office Supplies, North returns, and softer months create avoidable performance drag. | D4: Protect the strongest profit drivers while fixing underperforming categories, high-return regions, and weaker months through targeted pricing, operations, and promotion actions.
A5: Which product category is driving most revenue and profit? | B5: Electronics is the top-performing category | C5: Electronics generated the highest sales, about ₱5.73M, and the highest profit, about ₱852.9K. | D5: Increase inventory, prioritize marketing spend, and identify the best-selling electronics items to scale further.
A6: Which category needs pricing, cost, or demand review? | B6: Office Supplies is losing money | C6: Office Supplies had low sales, about ₱126K, and a negative profit of about -₱17.7K. | D6: Review supplier costs, pricing, discounts, and product mix. Consider reducing low-margin items or bundling them with stronger categories.
A7: Which region should be used as a benchmark for strong performance? | B7: East is the best-performing region | C7: East had the highest sales, highest profit, and the lowest return rate at 3.7%. | D7: Study East’s sales strategy, customer service process, and fulfillment practices, then apply the best practices to other regions.
A8: Where should we investigate customer dissatisfaction, product issues, or fulfillment problems? | B8: North has the highest return rate | C8: North’s return rate is 5.3%, higher than other regions. | D8: Check return reasons, delivery issues, product quality, and customer feedback in the North region. Focus on reducing avoidable returns.
A9: When do sales peak, and what caused the increase? | B9: June was the strongest sales month | C9: June reached the highest monthly sales and profit, suggesting a seasonal or campaign-driven spike. | D9: Review what promotions, campaigns, or seasonal factors happened in June and repeat them during slower months.
A10: Which months need stronger promotions or operational improvements? | B10: May and July were weaker months | C10: Sales and profit dropped noticeably in these months compared with stronger periods. | D10: Run targeted campaigns, discounts, loyalty offers, or product bundles during weaker months to stabilize revenue.
A11: Are good customer ratings translating into profitability? | B11: Customer rating is stable but does not guarantee profit | C11: The average rating is 4.3, and Office Supplies still has a decent rating despite being unprofitable. | D11: Combine customer satisfaction data with margin analysis. Focus not only on high-rated products, but also on products that are both profitable and well-rated.

Sheet Sales_Data
A1: Order_ID | B1: Order_Date | C1: Ship_Date | D1: Customer_ID | E1: Customer_Segment | F1: Country | G1: Region | H1: City | I1: Product_Category | J1: Product_Subcategory | K1: Product_Name | L1: Channel | M1: Payment_Method | N1: Quantity | O1: Unit_Price | P1: Discount | Q1: Shipping_Cost | R1: Sales | S1: Profit | T1: Returned | U1: Rating | V1: Delivery_Days | W1: Return_Value
A2: ORD-202500001 | B2: 45985 | C2: 45986 | D2: CUST-1006 | E2: Small Business | F2: Philippines | G2: South | H2: Davao City | I2: Electronics | J2: Laptop | K2: Laptop | L2: Marketplace | M2: Cash on Delivery | N2: 1 | O2: 52341.98 | P2: 0 | Q2: 989.75 | R2: =N2*O2*(1-P2) -> 52341.98 | S2: =R2*_xlfn.XLOOKUP(I2,Lookup_Lists!$A$2:$A$5,Lookup_Lists!$B$2:$B$5)-Q2-IF(T2="Yes",R2*0.2,0) -> 8431.8064 | T2: No | U2: 4.6 | V2: =C2-B2 -> 1 | W2: =IF(SalesDataTable[[#This Row],[Returned]]="Yes",1,0) -> 0
A3: ORD-202500002 | B3: 45990 | C3: 45996 | D3: CUST-1139 | E3: Consumer | F3: Philippines | G3: West | H3: Pasay | I3: Office Supplies | J3: Printer Paper | K3: Printer Paper | L3: Marketplace | M3: Debit Card | N3: 3 | O3: 412.47 | P3: 0 | Q3: 644.17 | R3: =N3*O3*(1-P3) -> 1237.41 | S3: =R3*_xlfn.XLOOKUP(I3,Lookup_Lists!$A$2:$A$5,Lookup_Lists!$B$2:$B$5)-Q3-IF(T3="Yes",R3*0.2,0) -> -248.1988 | T3: No | U3: 4.3 | V3: =C3-B3 -> 6 | W3: =IF(SalesDataTable[[#This Row],[Returned]]="Yes",1,0) -> 0
A4: ORD-202500003 | B4: 45705 | C4: 45709 | D4: CUST-1024 | E4: Consumer | F4: Philippines | G4: East | H4: Pasig | I4: Office Supplies | J4: Stapler | K4: Stapler | L4: Mobile App | M4: Bank Transfer | N4: 1 | O4: 251.67 | P4: 0.05 | Q4: 588.48 | R4: =N4*O4*(1-P4) -> 239.0865 | S4: =R4*_xlfn.XLOOKUP(I4,Lookup_Lists!$A$2:$A$5,Lookup_Lists!$B$2:$B$5)-Q4-IF(T4="Yes",R4*0.2,0) -> -511.97232 | T4: No | U4: 4.4 | V4: =C4-B4 -> 4 | W4: =IF(SalesDataTable[[#This Row],[Returned]]="Yes",1,0) -> 0
A5: ORD-202500004 | B5: 45996 | C5: 45998 | D5: CUST-1197 | E5: Consumer | F5: Philippines | G5: North | H5: Quezon City | I5: Home & Lifestyle | J5: Storage Bin | K5: Storage Bin | L5: Website | M5: E-Wallet | N5: 1 | O5: 542.62 | P5: 0.1 | Q5: 488.18 | R5: =N5*O5*(1-P5) -> 488.358 | S5: =R5*_xlfn.XLOOKUP(I5,Lookup_Lists!$A$2:$A$5,Lookup_Lists!$B$2:$B$5)-Q5-IF(T5="Yes",R5*0.2,0) -> -361.20692 | T5: No | U5: 4.5 | V5: =C5-B5 -> 2 | W5: =IF(SalesDataTable[[#This Row],[Returned]]="Yes",1,0) -> 0
A6: ORD-202500005 | B6: 45694 | C6: 45699 | D6: CUST-1162 | E6: Consumer | F6: Philippines | G6: South | H6: Davao City | I6: Furniture | J6: Bookshelf | K6: Bookshelf | L6: Social Commerce | M6: Cash on Delivery | N6: 1 | O6: 6352.35 | P6: 0.1 | Q6: 207.17 | R6: =N6*O6*(1-P6) -> 5717.115 | S6: =R6*_xlfn.XLOOKUP(I6,Lookup_Lists!$A$2:$A$5,Lookup_Lists!$B$2:$B$5)-Q6-IF(T6="Yes",R6*0.2,0) -> 1164.9376 | T6: No | U6: 4.5 | V6: =C6-B6 -> 5 | W6: =IF(SalesDataTable[[#This Row],[Returned]]="Yes",1,0) -> 0
A7: ORD-202500006 | B7: 45691 | C7: 45693 | D7: CUST-1145 | E7: Small Business | F7: Philippines | G7: East | H7: Marikina | I7: Office Supplies | J7: Stapler | K7: Stapler | L7: Retail Store | M7: Bank Transfer | N7: 1 | O7: 239.69 | P7: 0.1 | Q7: 390.81 | R7: =N7*O7*(1-P7) -> 215.721 | S7: =R7*_xlfn.XLOOKUP(I7,Lookup_Lists!$A$2:$A$5,Lookup_Lists!$B$2:$B$5)-Q7-IF(T7="Yes",R7*0.2,0) -> -321.77928 | T7: No | U7: 3.9 | V7: =C7-B7 -> 2 | W7: =IF(SalesDataTable[[#This Row],[Returned]]="Yes",1,0) -> 0
A8: ORD-202500007 | B8: 45877 | C8: 45882 | D8: CUST-1102 | E8: Consumer | F8: Philippines | G8: South | H8: Cagayan de Oro | I8: Electronics | J8: Laptop | K8: Laptop | L8: Retail Store | M8: Debit Card | N8: 3 | O8: 58116.44 | P8: 0 | Q8: 2731.45 | R8: =N8*O8*(1-P8) -> 174349.32 | S8: =R8*_xlfn.XLOOKUP(I8,Lookup_Lists!$A$2:$A$5,Lookup_Lists!$B$2:$B$5)-Q8-IF(T8="Yes",R8*0.2,0) -> 28651.428 | T8: No | U8: 4.9 | V8: =C8-B8 -> 5 | W8: =IF(SalesDataTable[[#This Row],[Returned]]="Yes",1,0) -> 0
A9: ORD-202500008 | B9: 45941 | C9: 45948 | D9: CUST-1002 | E9: Corporate | F9: Philippines | G9: North | H9: Baguio | I9: Office Supplies | J9: Pen Set | K9: Pen Set | L9: Website | M9: Bank Transfer | N9: 1 | O9: 158.58 | P9: 0.1 | Q9: 492.6 | R9: =N9*O9*(1-P9) -> 142.722 | S9: =R9*_xlfn.XLOOKUP(I9,Lookup_Lists!$A$2:$A$5,Lookup_Lists!$B$2:$B$5)-Q9-IF(T9="Yes",R9*0.2,0) -> -446.92896 | T9: No | U9: 4.2 | V9: =C9-B9 -> 7 | W9: =IF(SalesDataTable[[#This Row],[Returned]]="Yes",1,0) -> 0
A10: ORD-202500009 | B10: 45749 | C10: 45754 | D10: CUST-1027 | E10: Small Business | F10: Philippines | G10: East | H10: Marikina | I10: Electronics | J10: Monitor | K10: Monitor | L10: Mobile App | M10: Cash on Delivery | N10: 5 | O10: 11656.52 | P10: 0.05 | Q10: 1018 | R10: =N10*O10*(1-P10) -> 55368.47 | S10: =R10*_xlfn.XLOOKUP(I10,Lookup_Lists!$A$2:$A$5,Lookup_Lists!$B$2:$B$5)-Q10-IF(T10="Yes",R10*0.2,0) -> 8948.3246 | T10: No | U10: 5 | V10: =C10-B10 -> 5 | W10: =IF(SalesDataTable[[#This Row],[Returned]]="Yes",1,0) -> 0
A11: ORD-202500010 | B11: 45780 | C11: 45781 | D11: CUST-1061 | E11: Small Business | F11: Philippines | G11: North | H11: Manila | I11: Office Supplies | J11: Printer Paper | K11: Printer Paper | L11: Social Commerce | M11: Cash on Delivery | N11: 4 | O11: 385.78 | P11: 0.05 | Q11: 416.53 | R11: =N11*O11*(1-P11) -> 1465.964 | S11: =R11*_xlfn.XLOOKUP(I11,Lookup_Lists!$A$2:$A$5,Lookup_Lists!$B$2:$B$5)-Q11-IF(T11="Yes",R11*0.2,0) -> 52.57848 | T11: No | U11: 4.3 | V11: =C11-B11 -> 1 | W11: =IF(SalesDataTable[[#This Row],[Returned]]="Yes",1,0) -> 0
A12: ORD-202500011 | B12: 45968 | C12: 45972 | D12: CUST-1054 | E12: Home Office | F12: Philippines | G12: South | H12: Iloilo City | I12: Furniture | J12: Bookshelf | K12: Bookshelf | L12: Mobile App | M12: Cash on Delivery | N12: 2 | O12: 6203.42 | P12: 0 | Q12: 278.09 | R12: =N12*O12*(1-P12) -> 12406.84 | S12: =R12*_xlfn.XLOOKUP(I12,Lookup_Lists!$A$2:$A$5,Lookup_Lists!$B$2:$B$5)-Q12-IF(T12="Yes",R12*0.2,0) -> 2699.5516 | T12: No | U12: 4.3 | V12: =C12-B12 -> 4 | W12: =IF(SalesDataTable[[#This Row],[Returned]]="Yes",1,0) -> 0
A13: ORD-202500012 | B13: 46020 | C13: 46026 | D13: CUST-1015 | E13: Consumer | F13: Philippines | G13: North | H13: Baguio | I13: Electronics | J13: Monitor | K13: Monitor | L13: Website | M13: Bank Transfer | N13: 1 | O13: 10116.63 | P13: 0.2 | Q13: 557.24 | R13: =N13*O13*(1-P13) -> 8093.304 | S13: =R13*_xlfn.XLOOKUP(I13,Lookup_Lists!$A$2:$A$5,Lookup_Lists!$B$2:$B$5)-Q13-IF(T13="Yes",R13*0.2,0) -> 899.55472 | T13: No | U13: 4.2 | V13: =C13-B13 -> 6 | W13: =IF(SalesDataTable[[#This Row],[Returned]]="Yes",1,0) -> 0
... A501: ORD-202500500 | B501: 45800 | C501: 45805 | D501: CUST-1128 | E501: Corporate | F501: Philippines | G501: South | H501: Davao City | I501: Electronics | J501: Monitor | K501: Monitor | L501: Marketplace | M501: Debit Card | N501: 1 | O501: 11560.68 | P501: 0 | Q501: 551.57 | R501: =N501*O501*(1-P501) -> 11560.68 | S501: =R501*_xlfn.XLOOKUP(I501,Lookup_Lists!$A$2:$A$5,Lookup_Lists!$B$2:$B$5)-Q501-IF(T501="Yes",R501*0.2,0) -> 1529.3524 | T501: No | U501: 3.9 | V501: =C501-B501 -> 5 | W501: =IF(SalesDataTable[[#This Row],[Returned]]="Yes",1,0) -> 0

Sheet Lookup_Lists
A1: Product_Category | B1: Margin | D1: Customer_Segment | F1: Region | H1: Channel | J1: Payment_Method | L1: Returned
A2: Electronics | B2: 0.18 | D2: Consumer | F2: North | H2: Website | J2: Credit Card | L2: Yes
A3: Furniture | B3: 0.24 | D3: Corporate | F3: South | H3: Mobile App | J3: Debit Card | L3: No
A4: Office Supplies | B4: 0.32 | D4: Small Business | F4: East | H4: Marketplace | J4: E-Wallet
A5: Home & Lifestyle | B5: 0.26 | D5: Home Office | F5: West | H5: Retail Store | J5: Bank Transfer
H6: Social Commerce | J6: Cash on Delivery

Sheet Sales and Profit by Category
A3: Product_Category | B3: Total Sales | C3: Total Profit
A4: Electronics | B4: 5732221.2 | C4: 852895.48
A5: Furniture | B5: 2440570.9 | C5: 498103.66
A6: Home & Lifestyle | B6: 815273.69 | C6: 163090.55
A7: Office Supplies | B7: 126080.77 | C7: -17652.46
A8: Grand Total | B8: 9114146.6 | C8: 1496437.2
A27: Product_Category | B27: Total Sales | C27: Total Profit | D27: Average of Rating
A28: Electronics | B28: 5732221.2 | C28: 852895.48 | D28: 4.2988095
A29: Furniture | B29: 2440570.9 | C29: 498103.66 | D29: 4.2931373
A30: Home & Lifestyle | B30: 815273.69 | C30: 163090.55 | D30: 4.2807229
A31: Office Supplies | B31: 126080.77 | C31: -17652.46 | D31: 4.2061224
A32: Grand Total | B32: 9114146.6 | C32: 1496437.2 | D32: 4.2674

Sheet Sales and Profit by Region
A3: Region | B3: Total Sales | C3: Total Profit
A4: East | B4: 2607497.1 | C4: 418844.15
A5: North | B5: 2084247.9 | C5: 367803.04
A6: South | B6: 2268019.2 | C6: 363838.19
A7: West | B7: 2154382.4 | C7: 345951.84
A8: Grand Total | B8: 9114146.6 | C8: 1496437.2

Sheet Monthly Sales and Profit Trend
A3: Months (Order_Date) | B3: Total Sales | C3: Total Profit
A4: Jan | B4: 605987.07 | C4: 99784.884
A5: Feb | B5: 489588.35 | C5: 80249.472
A6: Mar | B6: 1218851.5 | C6: 198394.17
A7: Apr | B7: 959716.7 | C7: 154358.76
A8: May | B8: 347485.69 | C8: 51466.189
A9: Jun | B9: 1425448.7 | C9: 245588.69
A10: Jul | B10: 390605.01 | C10: 67516.88
A11: Aug | B11: 771290.9 | C11: 124616.21
A12: Sep | B12: 429680.15 | C12: 75723.353
A13: Oct | B13: 623210.09 | C13: 99176.011
A14: Nov | B14: 936248.44 | C14: 139943.52
A15: Dec | B15: 916034.02 | C15: 159619.08
A16: Grand Total | B16: 9114146.6 | C16: 1496437.2
A26: Months (Order_Date) | B26: Sales | C26: Profit | D26: Orders
A27: Jan | B27: 605987.07 | C27: 99784.884 | D27: 30 | G27: =A27&" "&"2025" -> Jan 2025 | H27: =B27 -> 605987.07 | I27: =C27 -> 99784.884 | J27: =D27 -> 30
A28: Feb | B28: 489588.35 | C28: 80249.472 | D28: 41 | G28: =A28&" "&"2025" -> Feb 2025 | H28: =B28 -> 489588.35 | I28: =C28 -> 80249.472 | J28: =D28 -> 41
A29: Mar | B29: 1218851.5 | C29: 198394.17 | D29: 47 | G29: =A29&" "&"2025" -> Mar 2025 | H29: =B29 -> 1218851.5 | I29: =C29 -> 198394.17 | J29: =D29 -> 47
A30: Apr | B30: 959716.7 | C30: 154358.76 | D30: 45 | G30: =A30&" "&"2025" -> Apr 2025 | H30: =B30 -> 959716.7 | I30: =C30 -> 154358.76 | J30: =D30 -> 45
A31: May | B31: 347485.69 | C31: 51466.189 | D31: 44 | G31: =A31&" "&"2025" -> May 2025 | H31: =B31 -> 347485.69 | I31: =C31 -> 51466.189 | J31: =D31 -> 44
A32: Jun | B32: 1425448.7 | C32: 245588.69 | D32: 42 | G32: =A32&" "&"2025" -> Jun 2025 | H32: =B32 -> 1425448.7 | I32: =C32 -> 245588.69 | J32: =D32 -> 42
A33: Jul | B33: 390605.01 | C33: 67516.88 | D33: 32 | G33: =A33&" "&"2025" -> Jul 2025 | H33: =B33 -> 390605.01 | I33: =C33 -> 67516.88 | J33: =D33 -> 32
A34: Aug | B34: 771290.9 | C34: 124616.21 | D34: 43 | G34: =A34&" "&"2025" -> Aug 2025 | H34: =B34 -> 771290.9 | I34: =C34 -> 124616.21 | J34: =D34 -> 43
A35: Sep | B35: 429680.15 | C35: 75723.353 | D35: 38 | G35: =A35&" "&"2025" -> Sep 2025 | H35: =B35 -> 429680.15 | I35: =C35 -> 75723.353 | J35: =D35 -> 38
A36: Oct | B36: 623210.09 | C36: 99176.011 | D36: 44 | G36: =A36&" "&"2025" -> Oct 2025 | H36: =B36 -> 623210.09 | I36: =C36 -> 99176.011 | J36: =D36 -> 44
A37: Nov | B37: 936248.44 | C37: 139943.52 | D37: 42 | G37: =A37&" "&"2025" -> Nov 2025 | H37: =B37 -> 936248.44 | I37: =C37 -> 139943.52 | J37: =D37 -> 42
A38: Dec | B38: 916034.02 | C38: 159619.08 | D38: 52 | G38: =A38&" "&"2025" -> Dec 2025 | H38: =B38 -> 916034.02 | I38: =C38 -> 159619.08 | J38: =D38 -> 52
A39: Grand Total | B39: 9114146.6 | C39: 1496437.2 | D39: 500
