Workbook
Name Slicer_Region: #N/A

Sheet Dashboard
A1: DASHBOARD
M3: Total Return Rate | R3: Customer Satisfaction Score
D11: Region | E11: Total Sales | F11: Total Profit | I11: Category | J11: Total Sales | K11: Total Profit
D12: =Analyze!B4 -> Central | E12: =Analyze!C4 -> 80334.25 | F12: =Analyze!D4 -> 34164.25 | I12: =Analyze!B14 -> Apparel | J12: =Analyze!C14 -> 21509.2 | K12: =Analyze!D14 -> 10159.2
D13: =Analyze!B5 -> Mindanao | E13: =Analyze!C5 -> 66400.38 | F13: =Analyze!D5 -> 26340.38 | I13: =Analyze!B15 -> Electronics | J13: =Analyze!C15 -> 187857.26 | K13: =Analyze!D15 -> 72967.26
D14: =Analyze!B6 -> North | E14: =Analyze!C6 -> 82148.65 | F14: =Analyze!D6 -> 34103.65 | I14: =Analyze!B16 -> Home | J14: =Analyze!C16 -> 33718 | K14: =Analyze!D16 -> 15348
D15: =Analyze!B7 -> South | E15: =Analyze!C7 -> 48793.28 | F15: =Analyze!D7 -> 19793.28 | I15: =Analyze!B17 -> Office Supplies | J15: =Analyze!C17 -> 34592.1 | K15: =Analyze!D17 -> 15927.1
D16: =Analyze!B8 -> Grand Total | E16: =Analyze!C8 -> 277676.56 | F16: =Analyze!D8 -> 114401.56 | I16: =Analyze!B18 -> Grand Total | J16: =Analyze!C18 -> 277676.56 | K16: =Analyze!D18 -> 114401.56
M18: Monthly Sales and Profit FY 2025
D19: Sales and Profit by Region | I19: Sales and Profit by Category

Sheet Analysis
A1: Dashboard Analysis
A2: Business question | B2: Insight | C2: Implication | D2: Suggested Action
A3: How is the business performing overall? | B3: Dashboard shows total sales of 277,677 and profit of 114,402, a 41.2% profit margin. Completed orders are 60%, returned orders 21%, cancelled orders 19%, and average satisfaction is 2.88 / 5. | C3: Profitability is strong, but 40% of orders not completing cleanly and a below-neutral satisfaction score create meaningful leakage risk. | D3: Prioritize reducing returns and cancellations while investigating satisfaction drivers by product, region, and fulfillment step.
A4: Which region leads sales? | B4: North leads with 82,149 sales and 34,104 profit, or 29.6% of total sales. Central is close behind with 80,334 sales and 34,164 profit. | C4: Revenue is concentrated in North and Central, suggesting these markets have the strongest current demand and execution. | D4: Protect stock availability and service levels in North/Central, then replicate their channel or promotion playbook in lower-performing regions.
A5: Which region needs the most attention? | B5: South is the lowest region with 48,793 sales and 19,793 profit, contributing only 17.6% of total sales. | C5: South underperformance limits total growth and may signal weaker demand generation, distribution, or customer fit. | D5: Run a South-region diagnostic on product mix, pricing, promotions, delivery performance, and customer feedback.
A6: Which region has the strongest margin? | B6: Central has the highest margin at 42.5%, followed by North at 41.5%, South at 40.6%, and Mindanao at 39.7%. | C6: Central appears to be the most efficient region, while Mindanao has the most margin improvement room. | D6: Use Central as the operating benchmark and test targeted margin actions in Mindanao.
A7: Which category drives revenue? | B7: Electronics generates 187,857 sales and 72,967 profit, representing 67.7% of total sales. | C7: The business is highly dependent on Electronics, creating concentration risk if demand, inventory, or supplier economics shift. | D7: Maintain Electronics availability and campaigns, but diversify growth into profitable non-Electronics categories.
A8: Which categories offer margin upside? | B8: Apparel has the highest margin at 47.2%, followed by Office Supplies at 46.0% and Home at 45.5%; Electronics margin is lower at 38.8%. | C8: Smaller categories are more profitable, so mix shift can improve profit even without proportional sales growth. | D8: Promote bundles, recommendations, and merchandising that attach Apparel, Office Supplies, and Home to Electronics orders.
A9: What is the strongest month? | B9: May is the best month with 47,321 sales and 19,416 profit, equal to 17.0% of annual sales. | C9: May likely reflects a successful campaign, seasonal lift, or operational peak that can inform repeatable planning. | D9: Investigate May drivers and reuse the strongest promotion, inventory, and channel tactics in future campaigns.
A10: What are the weakest months? | B10: November is the weakest month with 10,717 sales and 5,057 profit; September is also weak with 13,201 sales and 5,581 profit. | C10: Late-year softness or execution gaps create risk to steady sales coverage and resource planning. | D10: Create a September-to-November demand plan with targeted offers, inventory readiness, and weekly conversion tracking.
A11: Is monthly performance consistent? | B11: Monthly sales range from 10,717 in November to 47,321 in May, meaning the best month is about 4.4x the weakest month. | C11: High volatility makes inventory, staffing, and cash planning harder. | D11: Adopt a rolling monthly forecast and trigger review thresholds for months pacing materially below average.
A12: Are order outcomes healthy? | B12: Only 60% of orders are completed, while 21% are returned and 19% are cancelled. | C12: A 40% non-completion rate suggests substantial revenue leakage and possible customer experience issues. | D12: Set a near-term target to lift completed orders above 75% by reducing top cancellation and return causes.
A13: Is customer satisfaction adequate? | B13: Average satisfaction for completed orders is 2.88 / 5, equivalent to 57.7 on a 100-point gauge. | C13: Customer experience is below a healthy benchmark and may be linked to returns, repeat purchase risk, or support burden. | D13: Review low-score orders, survey detractors, and address service, delivery, and product-quality pain points.
A14: What is the highest-priority growth lever? | B14: The clearest opportunity is to improve South-region performance, grow high-margin non-Electronics categories, and reduce order leakage. | C14: These three levers can improve both revenue resilience and profitability without relying only on Electronics growth. | D14: Launch a 90-day action plan with KPIs for South sales, non-Electronics mix, completion rate, return rate, cancellation rate, and satisfaction.

Sheet Transactions
A1: Order ID | B1: Order Date | C1: Customer ID | D1: Product ID | E1: Sales Channel | F1: Payment Method | G1: Quantity | H1: Unit Price | I1: Discount % | J1: Shipping Fee | K1: Gross Sales | L1: Discount Amount | M1: Net Sales | N1: Unit Cost | O1: Total Cost | P1: Profit | Q1: Order Status | R1: Satisfaction Score
A2: ORD-0052 | B2: 45671 | C2: CUST-012 | D2: PROD-003 | E2: Retail | F2: Cash | G2: 2 | H2: 1450 | I2: 0.1 | J2: 0 | K2: 2900 | L2: 290 | M2: 2610 | N2: 850 | O2: 1700 | P2: 910 | Q2: Cancelled | R2: NA
A3: ORD-0078 | B3: 45672 | C3: CUST-002 | D3: PROD-004 | E3: Marketplace | F3: GCash | G3: 5 | H3: 1250 | I3: 0.1 | J3: 100 | K3: 6250 | L3: 625 | M3: 5725 | N3: 700 | O3: 3500 | P3: 2225 | Q3: Returned | R3: 1
A4: ORD-0099 | B4: 45677 | C4: CUST-003 | D4: PROD-011 | E4: Retail | F4: Cash | G4: 8 | H4: 273 | I4: 0.15 | J4: 0 | K4: 2184 | L4: 327.6 | M4: 1856.4 | N4: 130 | O4: 1040 | P4: 816.4 | Q4: Completed | R4: 1
A5: ORD-0083 | B5: 45680 | C5: CUST-011 | D5: PROD-014 | E5: Retail | F5: Cash | G5: 4 | H5: 270 | I5: 0.2 | J5: 100 | K5: 1080 | L5: 216 | M5: 964 | N5: 120 | O5: 480 | P5: 484 | Q5: Completed | R5: 4
A6: ORD-0048 | B6: 45683 | C6: CUST-013 | D6: PROD-010 | E6: Retail | F6: Cash | G6: 1 | H6: 722 | I6: 0.15 | J6: 50 | K6: 722 | L6: 108.3 | M6: 663.7 | N6: 420 | O6: 420 | P6: 243.7 | Q6: Returned | R6: 2
A7: ORD-0025 | B7: 45684 | C7: CUST-020 | D7: PROD-004 | E7: Online Store | F7: Cash | G7: 6 | H7: 1250 | I7: 0.1 | J7: 150 | K7: 7500 | L7: 750 | M7: 6900 | N7: 700 | O7: 4200 | P7: 2700 | Q7: Returned | R7: 3
A8: ORD-0005 | B8: 45690 | C8: CUST-002 | D8: PROD-014 | E8: Reseller | F8: Cash | G8: 2 | H8: 270 | I8: 0.05 | J8: 100 | K8: 540 | L8: 27 | M8: 613 | N8: 120 | O8: 240 | P8: 373 | Q8: Cancelled | R8: NA
A9: ORD-0019 | B9: 45693 | C9: CUST-002 | D9: PROD-001 | E9: Online Store | F9: GCash | G9: 8 | H9: 1650 | I9: 0 | J9: 150 | K9: 13200 | L9: 0 | M9: 13350 | N9: 950 | O9: 7600 | P9: 5750 | Q9: Completed | R9: 2
A10: ORD-0013 | B10: 45706 | C10: CUST-016 | D10: PROD-004 | E10: Online Store | F10: Cash | G10: 3 | H10: 1375 | I10: 0.05 | J10: 100 | K10: 4125 | L10: 206.25 | M10: 4018.75 | N10: 700 | O10: 2100 | P10: 1918.75 | Q10: Returned | R10: 2
A11: ORD-0007 | B11: 45712 | C11: CUST-006 | D11: PROD-008 | E11: Retail | F11: GCash | G11: 1 | H11: 399 | I11: 0.2 | J11: 50 | K11: 399 | L11: 79.8 | M11: 369.2 | N11: 210 | O11: 210 | P11: 159.2 | Q11: Cancelled | R11: NA
A12: ORD-0006 | B12: 45715 | C12: CUST-020 | D12: PROD-008 | E12: Retail | F12: Cash | G12: 5 | H12: 361 | I12: 0 | J12: 150 | K12: 1805 | L12: 0 | M12: 1955 | N12: 210 | O12: 1050 | P12: 905 | Q12: Completed | R12: 3
A13: ORD-0008 | B13: 45715 | C13: CUST-005 | D13: PROD-006 | E13: Retail | F13: Bank Transfer | G13: 3 | H13: 85.5 | I13: 0.2 | J13: 75 | K13: 256.5 | L13: 51.3 | M13: 280.2 | N13: 45 | O13: 135 | P13: 145.2 | Q13: Returned | R13: 1
A14: ORD-0033 | B14: 45717 | C14: CUST-020 | D14: PROD-007 | E14: Reseller | F14: GCash | G14: 6 | H14: 357 | I14: 0.15 | J14: 150 | K14: 2142 | L14: 321.3 | M14: 1970.7 | N14: 180 | O14: 1080 | P14: 890.7 | Q14: Cancelled | R14: NA
A15: ORD-0079 | B15: 45718 | C15: CUST-010 | D15: PROD-009 | E15: Marketplace | F15: Cash | G15: 1 | H15: 187 | I15: 0 | J15: 50 | K15: 187 | L15: 0 | M15: 237 | N15: 90 | O15: 90 | P15: 147 | Q15: Completed | R15: 4
A16: ORD-0097 | B16: 45721 | C16: CUST-018 | D16: PROD-006 | E16: Reseller | F16: Bank Transfer | G16: 2 | H16: 99 | I16: 0 | J16: 75 | K16: 198 | L16: 0 | M16: 273 | N16: 45 | O16: 90 | P16: 183 | Q16: Cancelled | R16: NA
A17: ORD-0009 | B17: 45722 | C17: CUST-008 | D17: PROD-001 | E17: Marketplace | F17: Cash | G17: 4 | H17: 1567.5 | I17: 0 | J17: 100 | K17: 6270 | L17: 0 | M17: 6370 | N17: 950 | O17: 3800 | P17: 2570 | Q17: Completed | R17: 5
A18: ORD-0063 | B18: 45722 | C18: CUST-010 | D18: PROD-004 | E18: Retail | F18: Credit Card | G18: 6 | H18: 1250 | I18: 0.1 | J18: 0 | K18: 7500 | L18: 750 | M18: 6750 | N18: 700 | O18: 4200 | P18: 2550 | Q18: Cancelled | R18: NA
A19: ORD-0004 | B19: 45728 | C19: CUST-018 | D19: PROD-009 | E19: Reseller | F19: Credit Card | G19: 5 | H19: 187 | I19: 0.2 | J19: 100 | K19: 935 | L19: 187 | M19: 848 | N19: 90 | O19: 450 | P19: 398 | Q19: Completed | R19: 2
A20: ORD-0096 | B20: 45730 | C20: CUST-006 | D20: PROD-005 | E20: Marketplace | F20: Cash | G20: 8 | H20: 157.5 | I20: 0.1 | J20: 0 | K20: 1260 | L20: 126 | M20: 1134 | N20: 80 | O20: 640 | P20: 494 | Q20: Returned | R20: 1
A21: ORD-0027 | B21: 45733 | C21: CUST-004 | D21: PROD-002 | E21: Reseller | F21: GCash | G21: 3 | H21: 589 | I21: 0.1 | J21: 150 | K21: 1767 | L21: 176.7 | M21: 1740.3 | N21: 310 | O21: 930 | P21: 810.3 | Q21: Cancelled | R21: NA
A22: ORD-0038 | B22: 45733 | C22: CUST-003 | D22: PROD-005 | E22: Online Store | F22: Credit Card | G22: 6 | H22: 142.5 | I22: 0.05 | J22: 75 | K22: 855 | L22: 42.75 | M22: 887.25 | N22: 80 | O22: 480 | P22: 407.25 | Q22: Completed | R22: 2
A23: ORD-0024 | B23: 45737 | C23: CUST-018 | D23: PROD-005 | E23: Retail | F23: Bank Transfer | G23: 2 | H23: 150 | I23: 0.1 | J23: 0 | K23: 300 | L23: 30 | M23: 270 | N23: 80 | O23: 160 | P23: 110 | Q23: Completed | R23: 5
A24: ORD-0091 | B24: 45759 | C24: CUST-003 | D24: PROD-008 | E24: Reseller | F24: Cash | G24: 6 | H24: 399 | I24: 0.15 | J24: 75 | K24: 2394 | L24: 359.1 | M24: 2109.9 | N24: 210 | O24: 1260 | P24: 849.9 | Q24: Returned | R24: 3
A25: ORD-0051 | B25: 45769 | C25: CUST-020 | D25: PROD-003 | E25: Reseller | F25: Bank Transfer | G25: 4 | H25: 1450 | I25: 0.15 | J25: 0 | K25: 5800 | L25: 870 | M25: 4930 | N25: 850 | O25: 3400 | P25: 1530 | Q25: Cancelled | R25: NA
A26: ORD-0046 | B26: 45770 | C26: CUST-012 | D26: PROD-005 | E26: Reseller | F26: GCash | G26: 7 | H26: 165 | I26: 0.2 | J26: 150 | K26: 1155 | L26: 231 | M26: 1074 | N26: 80 | O26: 560 | P26: 514 | Q26: Cancelled | R26: NA
A27: ORD-0073 | B27: 45775 | C27: CUST-020 | D27: PROD-001 | E27: Online Store | F27: Bank Transfer | G27: 7 | H27: 1732.5 | I27: 0.2 | J27: 75 | K27: 12127.5 | L27: 2425.5 | M27: 9777 | N27: 950 | O27: 6650 | P27: 3127 | Q27: Completed | R27: 1
A28: ORD-0069 | B28: 45776 | C28: CUST-006 | D28: PROD-001 | E28: Retail | F28: Bank Transfer | G28: 7 | H28: 1815 | I28: 0.2 | J28: 100 | K28: 12705 | L28: 2541 | M28: 10264 | N28: 950 | O28: 6650 | P28: 3614 | Q28: Completed | R28: 1
A29: ORD-0068 | B29: 45780 | C29: CUST-020 | D29: PROD-012 | E29: Marketplace | F29: Credit Card | G29: 2 | H29: 300 | I29: 0.05 | J29: 75 | K29: 600 | L29: 30 | M29: 645 | N29: 160 | O29: 320 | P29: 325 | Q29: Completed | R29: 2
A30: ORD-0056 | B30: 45782 | C30: CUST-015 | D30: PROD-007 | E30: Reseller | F30: Cash | G30: 5 | H30: 357 | I30: 0.05 | J30: 0 | K30: 1785 | L30: 89.25 | M30: 1695.75 | N30: 180 | O30: 900 | P30: 795.75 | Q30: Completed | R30: 4
A31: ORD-0001 | B31: 45783 | C31: CUST-007 | D31: PROD-011 | E31: Marketplace | F31: Cash | G31: 5 | H31: 247 | I31: 0.2 | J31: 50 | K31: 1235 | L31: 247 | M31: 1038 | N31: 130 | O31: 650 | P31: 388 | Q31: Cancelled | R31: NA
A32: ORD-0050 | B32: 45784 | C32: CUST-001 | D32: PROD-012 | E32: Marketplace | F32: Credit Card | G32: 1 | H32: 315 | I32: 0.05 | J32: 0 | K32: 315 | L32: 15.75 | M32: 299.25 | N32: 160 | O32: 160 | P32: 139.25 | Q32: Completed | R32: 1
A33: ORD-0015 | B33: 45785 | C33: CUST-007 | D33: PROD-004 | E33: Online Store | F33: Cash | G33: 8 | H33: 1250 | I33: 0.15 | J33: 50 | K33: 10000 | L33: 1500 | M33: 8550 | N33: 700 | O33: 5600 | P33: 2950 | Q33: Completed | R33: 4
A34: ORD-0066 | B34: 45785 | C34: CUST-019 | D34: PROD-011 | E34: Online Store | F34: Cash | G34: 1 | H34: 260 | I34: 0.05 | J34: 150 | K34: 260 | L34: 13 | M34: 397 | N34: 130 | O34: 130 | P34: 267 | Q34: Completed | R34: 1
A35: ORD-0049 | B35: 45787 | C35: CUST-011 | D35: PROD-004 | E35: Online Store | F35: Cash | G35: 8 | H35: 1312.5 | I35: 0.1 | J35: 100 | K35: 10500 | L35: 1050 | M35: 9550 | N35: 700 | O35: 5600 | P35: 3950 | Q35: Completed | R35: 4
A36: ORD-0057 | B36: 45790 | C36: CUST-011 | D36: PROD-001 | E36: Retail | F36: Bank Transfer | G36: 8 | H36: 1732.5 | I36: 0.05 | J36: 100 | K36: 13860 | L36: 693 | M36: 13267 | N36: 950 | O36: 7600 | P36: 5667 | Q36: Completed | R36: 3
A37: ORD-0003 | B37: 45793 | C37: CUST-007 | D37: PROD-015 | E37: Marketplace | F37: GCash | G37: 6 | H37: 900 | I37: 0.15 | J37: 100 | K37: 5400 | L37: 810 | M37: 4690 | N37: 450 | O37: 2700 | P37: 1990 | Q37: Returned | R37: 2
A38: ORD-0022 | B38: 45793 | C38: CUST-001 | D38: PROD-008 | E38: Marketplace | F38: Bank Transfer | G38: 2 | H38: 361 | I38: 0.2 | J38: 50 | K38: 722 | L38: 144.4 | M38: 627.6 | N38: 210 | O38: 420 | P38: 207.6 | Q38: Cancelled | R38: NA
A39: ORD-0032 | B39: 45793 | C39: CUST-018 | D39: PROD-006 | E39: Online Store | F39: Credit Card | G39: 1 | H39: 85.5 | I39: 0.1 | J39: 50 | K39: 85.5 | L39: 8.55 | M39: 126.95 | N39: 45 | O39: 45 | P39: 81.95 | Q39: Cancelled | R39: NA
A40: ORD-0081 | B40: 45794 | C40: CUST-007 | D40: PROD-015 | E40: Online Store | F40: Bank Transfer | G40: 3 | H40: 855 | I40: 0.1 | J40: 100 | K40: 2565 | L40: 256.5 | M40: 2408.5 | N40: 450 | O40: 1350 | P40: 1058.5 | Q40: Completed | R40: 5
A41: ORD-0031 | B41: 45800 | C41: CUST-008 | D41: PROD-004 | E41: Retail | F41: Cash | G41: 1 | H41: 1250 | I41: 0.15 | J41: 75 | K41: 1250 | L41: 187.5 | M41: 1137.5 | N41: 700 | O41: 700 | P41: 437.5 | Q41: Completed | R41: 1
A42: ORD-0062 | B42: 45802 | C42: CUST-007 | D42: PROD-012 | E42: Online Store | F42: GCash | G42: 8 | H42: 315 | I42: 0.2 | J42: 150 | K42: 2520 | L42: 504 | M42: 2166 | N42: 160 | O42: 1280 | P42: 886 | Q42: Cancelled | R42: NA
A43: ORD-0064 | B43: 45803 | C43: CUST-002 | D43: PROD-009 | E43: Reseller | F43: Cash | G43: 5 | H43: 170 | I43: 0.15 | J43: 0 | K43: 850 | L43: 127.5 | M43: 722.5 | N43: 90 | O43: 450 | P43: 272.5 | Q43: Completed | R43: 5
A44: ORD-0041 | B44: 45820 | C44: CUST-004 | D44: PROD-008 | E44: Reseller | F44: Cash | G44: 3 | H44: 418 | I44: 0.2 | J44: 150 | K44: 1254 | L44: 250.8 | M44: 1153.2 | N44: 210 | O44: 630 | P44: 523.2 | Q44: Cancelled | R44: NA
A45: ORD-0076 | B45: 45823 | C45: CUST-010 | D45: PROD-011 | E45: Online Store | F45: Cash | G45: 7 | H45: 247 | I45: 0.15 | J45: 0 | K45: 1729 | L45: 259.35 | M45: 1469.65 | N45: 130 | O45: 910 | P45: 559.65 | Q45: Completed | R45: 3
A46: ORD-0075 | B46: 45826 | C46: CUST-003 | D46: PROD-008 | E46: Reseller | F46: Cash | G46: 6 | H46: 418 | I46: 0.1 | J46: 75 | K46: 2508 | L46: 250.8 | M46: 2332.2 | N46: 210 | O46: 1260 | P46: 1072.2 | Q46: Completed | R46: 2
A47: ORD-0044 | B47: 45827 | C47: CUST-005 | D47: PROD-004 | E47: Reseller | F47: Cash | G47: 7 | H47: 1250 | I47: 0.05 | J47: 0 | K47: 8750 | L47: 437.5 | M47: 8312.5 | N47: 700 | O47: 4900 | P47: 3412.5 | Q47: Returned | R47: 4
A48: ORD-0082 | B48: 45828 | C48: CUST-010 | D48: PROD-014 | E48: Reseller | F48: Cash | G48: 8 | H48: 270 | I48: 0.15 | J48: 150 | K48: 2160 | L48: 324 | M48: 1986 | N48: 120 | O48: 960 | P48: 1026 | Q48: Returned | R48: 3
A49: ORD-0014 | B49: 45831 | C49: CUST-012 | D49: PROD-007 | E49: Online Store | F49: GCash | G49: 7 | H49: 374 | I49: 0 | J49: 0 | K49: 2618 | L49: 0 | M49: 2618 | N49: 180 | O49: 1260 | P49: 1358 | Q49: Completed | R49: 4
A50: ORD-0093 | B50: 45838 | C50: CUST-001 | D50: PROD-010 | E50: Marketplace | F50: GCash | G50: 1 | H50: 836 | I50: 0.1 | J50: 50 | K50: 836 | L50: 83.6 | M50: 802.4 | N50: 420 | O50: 420 | P50: 382.4 | Q50: Cancelled | R50: NA
A51: ORD-0028 | B51: 45839 | C51: CUST-002 | D51: PROD-005 | E51: Reseller | F51: GCash | G51: 6 | H51: 142.5 | I51: 0.1 | J51: 50 | K51: 855 | L51: 85.5 | M51: 819.5 | N51: 80 | O51: 480 | P51: 339.5 | Q51: Completed | R51: 1
A52: ORD-0088 | B52: 45841 | C52: CUST-006 | D52: PROD-012 | E52: Retail | F52: Cash | G52: 5 | H52: 285 | I52: 0 | J52: 75 | K52: 1425 | L52: 0 | M52: 1500 | N52: 160 | O52: 800 | P52: 700 | Q52: Completed | R52: 3
A53: ORD-0077 | B53: 45843 | C53: CUST-017 | D53: PROD-014 | E53: Reseller | F53: Cash | G53: 1 | H53: 297 | I53: 0.15 | J53: 0 | K53: 297 | L53: 44.55 | M53: 252.45 | N53: 120 | O53: 120 | P53: 132.45 | Q53: Completed | R53: 5
A54: ORD-0045 | B54: 45852 | C54: CUST-002 | D54: PROD-004 | E54: Reseller | F54: Credit Card | G54: 7 | H54: 1375 | I54: 0.2 | J54: 0 | K54: 9625 | L54: 1925 | M54: 7700 | N54: 700 | O54: 4900 | P54: 2800 | Q54: Cancelled | R54: NA
A55: ORD-0089 | B55: 45853 | C55: CUST-005 | D55: PROD-004 | E55: Marketplace | F55: Cash | G55: 7 | H55: 1250 | I55: 0.05 | J55: 50 | K55: 8750 | L55: 437.5 | M55: 8362.5 | N55: 700 | O55: 4900 | P55: 3462.5 | Q55: Completed | R55: 5
A56: ORD-0010 | B56: 45862 | C56: CUST-018 | D56: PROD-003 | E56: Retail | F56: Cash | G56: 5 | H56: 1595 | I56: 0.05 | J56: 150 | K56: 7975 | L56: 398.75 | M56: 7726.25 | N56: 850 | O56: 4250 | P56: 3476.25 | Q56: Completed | R56: 3
A57: ORD-0002 | B57: 45863 | C57: CUST-013 | D57: PROD-005 | E57: Retail | F57: Credit Card | G57: 4 | H57: 157.5 | I57: 0 | J57: 50 | K57: 630 | L57: 0 | M57: 680 | N57: 80 | O57: 320 | P57: 360 | Q57: Completed | R57: 3
A58: ORD-0065 | B58: 45863 | C58: CUST-015 | D58: PROD-006 | E58: Reseller | F58: Credit Card | G58: 3 | H58: 85.5 | I58: 0.1 | J58: 100 | K58: 256.5 | L58: 25.65 | M58: 330.85 | N58: 45 | O58: 135 | P58: 195.85 | Q58: Completed | R58: 1
A59: ORD-0035 | B59: 45864 | C59: CUST-020 | D59: PROD-006 | E59: Retail | F59: GCash | G59: 2 | H59: 94.5 | I59: 0.2 | J59: 75 | K59: 189 | L59: 37.8 | M59: 226.2 | N59: 45 | O59: 90 | P59: 136.2 | Q59: Returned | R59: 3
A60: ORD-0059 | B60: 45865 | C60: CUST-016 | D60: PROD-011 | E60: Marketplace | F60: Bank Transfer | G60: 8 | H60: 286 | I60: 0 | J60: 0 | K60: 2288 | L60: 0 | M60: 2288 | N60: 130 | O60: 1040 | P60: 1248 | Q60: Completed | R60: 2
A61: ORD-0058 | B61: 45866 | C61: CUST-020 | D61: PROD-012 | E61: Reseller | F61: GCash | G61: 5 | H61: 285 | I61: 0.2 | J61: 50 | K61: 1425 | L61: 285 | M61: 1190 | N61: 160 | O61: 800 | P61: 390 | Q61: Completed | R61: 2
A62: ORD-0029 | B62: 45868 | C62: CUST-008 | D62: PROD-014 | E62: Marketplace | F62: Bank Transfer | G62: 3 | H62: 270 | I62: 0.15 | J62: 0 | K62: 810 | L62: 121.5 | M62: 688.5 | N62: 120 | O62: 360 | P62: 328.5 | Q62: Completed | R62: 3
A63: ORD-0100 | B63: 45872 | C63: CUST-004 | D63: PROD-002 | E63: Marketplace | F63: Cash | G63: 4 | H63: 620 | I63: 0.15 | J63: 100 | K63: 2480 | L63: 372 | M63: 2208 | N63: 310 | O63: 1240 | P63: 968 | Q63: Completed | R63: 5
A64: ORD-0054 | B64: 45873 | C64: CUST-012 | D64: PROD-009 | E64: Reseller | F64: Credit Card | G64: 7 | H64: 178.5 | I64: 0 | J64: 150 | K64: 1249.5 | L64: 0 | M64: 1399.5 | N64: 90 | O64: 630 | P64: 769.5 | Q64: Completed | R64: 1
A65: ORD-0067 | B65: 45877 | C65: CUST-020 | D65: PROD-010 | E65: Retail | F65: Credit Card | G65: 4 | H65: 836 | I65: 0.15 | J65: 100 | K65: 3344 | L65: 501.6 | M65: 2942.4 | N65: 420 | O65: 1680 | P65: 1262.4 | Q65: Completed | R65: 5
A66: ORD-0034 | B66: 45878 | C66: CUST-009 | D66: PROD-001 | E66: Online Store | F66: Bank Transfer | G66: 7 | H66: 1567.5 | I66: 0.2 | J66: 150 | K66: 10972.5 | L66: 2194.5 | M66: 8928 | N66: 950 | O66: 6650 | P66: 2278 | Q66: Completed | R66: 3
... A74: ORD-0016 | B74: 45906 | C74: CUST-018 | D74: PROD-002 | E74: Reseller | F74: GCash | G74: 1 | H74: 589 | I74: 0 | J74: 50 | K74: 589 | L74: 0 | M74: 639 | N74: 310 | O74: 310 | P74: 329 | Q74: Completed | R74: 4
A75: ORD-0072 | B75: 45910 | C75: CUST-004 | D75: PROD-008 | E75: Reseller | F75: Credit Card | G75: 5 | H75: 418 | I75: 0.1 | J75: 150 | K75: 2090 | L75: 209 | M75: 2031 | N75: 210 | O75: 1050 | P75: 981 | Q75: Cancelled | R75: NA
A76: ORD-0039 | B76: 45911 | C76: CUST-008 | D76: PROD-008 | E76: Reseller | F76: GCash | G76: 2 | H76: 418 | I76: 0.15 | J76: 150 | K76: 836 | L76: 125.4 | M76: 860.6 | N76: 210 | O76: 420 | P76: 440.6 | Q76: Completed | R76: 4
A77: ORD-0037 | B77: 45919 | C77: CUST-010 | D77: PROD-004 | E77: Reseller | F77: GCash | G77: 7 | H77: 1312.5 | I77: 0.15 | J77: 100 | K77: 9187.5 | L77: 1378.12 | M77: 7909.38 | N77: 700 | O77: 4900 | P77: 3009.38 | Q77: Returned | R77: 2
A78: ORD-0012 | B78: 45921 | C78: CUST-001 | D78: PROD-002 | E78: Marketplace | F78: Bank Transfer | G78: 1 | H78: 620 | I78: 0 | J78: 0 | K78: 620 | L78: 0 | M78: 620 | N78: 310 | O78: 310 | P78: 310 | Q78: Completed | R78: 1
A79: ORD-0042 | B79: 45924 | C79: CUST-018 | D79: PROD-008 | E79: Reseller | F79: GCash | G79: 3 | H79: 418 | I79: 0.15 | J79: 75 | K79: 1254 | L79: 188.1 | M79: 1140.9 | N79: 210 | O79: 630 | P79: 510.9 | Q79: Completed | R79: 3
A80: ORD-0043 | B80: 45934 | C80: CUST-009 | D80: PROD-008 | E80: Online Store | F80: GCash | G80: 2 | H80: 399 | I80: 0.05 | J80: 75 | K80: 798 | L80: 39.9 | M80: 833.1 | N80: 210 | O80: 420 | P80: 413.1 | Q80: Completed | R80: 3
A81: ORD-0095 | B81: 45934 | C81: CUST-003 | D81: PROD-015 | E81: Retail | F81: Bank Transfer | G81: 5 | H81: 945 | I81: 0.15 | J81: 50 | K81: 4725 | L81: 708.75 | M81: 4066.25 | N81: 450 | O81: 2250 | P81: 1816.25 | Q81: Completed | R81: 2
A82: ORD-0070 | B82: 45936 | C82: CUST-015 | D82: PROD-002 | E82: Marketplace | F82: GCash | G82: 4 | H82: 651 | I82: 0.2 | J82: 50 | K82: 2604 | L82: 520.8 | M82: 2133.2 | N82: 310 | O82: 1240 | P82: 893.2 | Q82: Returned | R82: 1
A83: ORD-0036 | B83: 45938 | C83: CUST-007 | D83: PROD-007 | E83: Online Store | F83: Bank Transfer | G83: 7 | H83: 340 | I83: 0.2 | J83: 150 | K83: 2380 | L83: 476 | M83: 2054 | N83: 180 | O83: 1260 | P83: 794 | Q83: Completed | R83: 4
A84: ORD-0026 | B84: 45940 | C84: CUST-009 | D84: PROD-001 | E84: Reseller | F84: Credit Card | G84: 1 | H84: 1732.5 | I84: 0.05 | J84: 75 | K84: 1732.5 | L84: 86.62 | M84: 1720.88 | N84: 950 | O84: 950 | P84: 770.88 | Q84: Completed | R84: 4
A85: ORD-0080 | B85: 45940 | C85: CUST-010 | D85: PROD-009 | E85: Marketplace | F85: Cash | G85: 5 | H85: 187 | I85: 0.15 | J85: 100 | K85: 935 | L85: 140.25 | M85: 894.75 | N85: 90 | O85: 450 | P85: 444.75 | Q85: Completed | R85: 4
A86: ORD-0020 | B86: 45947 | C86: CUST-013 | D86: PROD-002 | E86: Retail | F86: Bank Transfer | G86: 4 | H86: 589 | I86: 0.2 | J86: 0 | K86: 2356 | L86: 471.2 | M86: 1884.8 | N86: 310 | O86: 1240 | P86: 644.8 | Q86: Returned | R86: 5
A87: ORD-0071 | B87: 45949 | C87: CUST-009 | D87: PROD-014 | E87: Retail | F87: Cash | G87: 3 | H87: 256.5 | I87: 0 | J87: 50 | K87: 769.5 | L87: 0 | M87: 819.5 | N87: 120 | O87: 360 | P87: 459.5 | Q87: Completed | R87: 5
... A91: ORD-0011 | B91: 45959 | C91: CUST-017 | D91: PROD-008 | E91: Marketplace | F91: GCash | G91: 2 | H91: 380 | I91: 0.05 | J91: 0 | K91: 760 | L91: 38 | M91: 722 | N91: 210 | O91: 420 | P91: 302 | Q91: Completed | R91: 1
A92: ORD-0084 | B92: 45960 | C92: CUST-013 | D92: PROD-007 | E92: Retail | F92: Credit Card | G92: 3 | H92: 374 | I92: 0 | J92: 50 | K92: 1122 | L92: 0 | M92: 1172 | N92: 180 | O92: 540 | P92: 632 | Q92: Cancelled | R92: NA
A93: ORD-0098 | B93: 45975 | C93: CUST-009 | D93: PROD-010 | E93: Retail | F93: GCash | G93: 7 | H93: 798 | I93: 0 | J93: 50 | K93: 5586 | L93: 0 | M93: 5636 | N93: 420 | O93: 2940 | P93: 2696 | Q93: Returned | R93: 1
A94: ORD-0086 | B94: 45978 | C94: CUST-020 | D94: PROD-012 | E94: Reseller | F94: Credit Card | G94: 7 | H94: 285 | I94: 0.1 | J94: 150 | K94: 1995 | L94: 199.5 | M94: 1945.5 | N94: 160 | O94: 1120 | P94: 825.5 | Q94: Returned | R94: 3
A95: ORD-0087 | B95: 45982 | C95: CUST-020 | D95: PROD-002 | E95: Online Store | F95: Cash | G95: 4 | H95: 651 | I95: 0.05 | J95: 0 | K95: 2604 | L95: 130.2 | M95: 2473.8 | N95: 310 | O95: 1240 | P95: 1233.8 | Q95: Returned | R95: 1
A96: ORD-0055 | B96: 45991 | C96: CUST-014 | D96: PROD-006 | E96: Retail | F96: Cash | G96: 8 | H96: 90 | I96: 0.15 | J96: 50 | K96: 720 | L96: 108 | M96: 662 | N96: 45 | O96: 360 | P96: 302 | Q96: Cancelled | R96: NA
A97: ORD-0092 | B97: 45995 | C97: CUST-004 | D97: PROD-004 | E97: Reseller | F97: Bank Transfer | G97: 7 | H97: 1312.5 | I97: 0.2 | J97: 75 | K97: 9187.5 | L97: 1837.5 | M97: 7425 | N97: 700 | O97: 4900 | P97: 2525 | Q97: Completed | R97: 1
A98: ORD-0053 | B98: 46008 | C98: CUST-013 | D98: PROD-012 | E98: Online Store | F98: Credit Card | G98: 4 | H98: 285 | I98: 0.2 | J98: 50 | K98: 1140 | L98: 228 | M98: 962 | N98: 160 | O98: 640 | P98: 322 | Q98: Completed | R98: 3
A99: ORD-0061 | B99: 46011 | C99: CUST-010 | D99: PROD-005 | E99: Marketplace | F99: GCash | G99: 4 | H99: 142.5 | I99: 0.05 | J99: 75 | K99: 570 | L99: 28.5 | M99: 616.5 | N99: 80 | O99: 320 | P99: 296.5 | Q99: Completed | R99: 5
A100: ORD-0060 | B100: 46017 | C100: CUST-019 | D100: PROD-006 | E100: Reseller | F100: Bank Transfer | G100: 8 | H100: 94.5 | I100: 0.15 | J100: 150 | K100: 756 | L100: 113.4 | M100: 792.6 | N100: 45 | O100: 360 | P100: 432.6 | Q100: Completed | R100: 3
A101: ORD-0023 | B101: 46018 | C101: CUST-003 | D101: PROD-015 | E101: Retail | F101: Credit Card | G101: 4 | H101: 945 | I101: 0.1 | J101: 50 | K101: 3780 | L101: 378 | M101: 3452 | N101: 450 | O101: 1800 | P101: 1652 | Q101: Returned | R101: 5

Sheet Customers
A1: Customer ID | B1: Customer Name | C1: Segment | D1: Region | E1: City | F1: Signup Date
A2: CUST-001 | B2: Customer 01 | C2: Consumer | D2: North | E2: Caloocan | F2: 45208
A3: CUST-002 | B3: Customer 02 | C3: Consumer | D3: South | E3: Makati | F3: 45681
A4: CUST-003 | B4: Customer 03 | C4: Small Business | D4: North | E4: Caloocan | F4: 45485
A5: CUST-004 | B5: Customer 04 | C5: Small Business | D5: North | E5: Manila | F5: 44959
A6: CUST-005 | B6: Customer 05 | C6: Consumer | D6: North | E6: Quezon City | F6: 45165
A7: CUST-006 | B7: Customer 06 | C7: Small Business | D7: North | E7: Quezon City | F7: 45660
A8: CUST-007 | B8: Customer 07 | C8: Consumer | D8: Mindanao | E8: Cagayan de Oro | F8: 45530
A9: CUST-008 | B9: Customer 08 | C9: Consumer | D9: Central | E9: Cebu City | F9: 45641
A10: CUST-009 | B10: Customer 09 | C10: Corporate | D10: Mindanao | E10: Cagayan de Oro | F10: 45086
A11: CUST-010 | B11: Customer 10 | C11: Corporate | D11: South | E11: Makati | F11: 45021
A12: CUST-011 | B12: Customer 11 | C12: Consumer | D12: Mindanao | E12: Cagayan de Oro | F12: 45794
A13: CUST-012 | B13: Customer 12 | C13: Small Business | D13: Central | E13: Mandaue | F13: 45753
... A21: CUST-020 | B21: Customer 20 | C21: Consumer | D21: Central | E21: Mandaue | F21: 45290

Sheet Analyze
B3: Row Labels | C3: Sum of Net Sales | D3: Sum of Profit
B4: Central | C4: 80334.25 | D4: 34164.25 | F4: =B4 -> Central | G4: =C4 -> 80334.25 | H4: =D4 -> 34164.25
B5: Mindanao | C5: 66400.38 | D5: 26340.38 | F5: =B5 -> Mindanao | G5: =C5 -> 66400.38 | H5: =D5 -> 26340.38
B6: North | C6: 82148.65 | D6: 34103.65 | F6: =B6 -> North | G6: =C6 -> 82148.65 | H6: =D6 -> 34103.65
B7: South | C7: 48793.28 | D7: 19793.28 | F7: =B7 -> South | G7: =C7 -> 48793.28 | H7: =D7 -> 19793.28
B8: Grand Total | C8: 277676.56 | D8: 114401.56
B13: Row Labels | C13: Sum of Net Sales | D13: Sum of Profit
B14: Apparel | C14: 21509.2 | D14: 10159.2 | F14: =B14 -> Apparel | G14: =C14 -> 21509.2 | H14: =D14 -> 10159.2
B15: Electronics | C15: 187857.26 | D15: 72967.26 | F15: =B15 -> Electronics | G15: =C15 -> 187857.26 | H15: =D15 -> 72967.26
B16: Home | C16: 33718 | D16: 15348 | F16: =B16 -> Home | G16: =C16 -> 33718 | H16: =D16 -> 15348
B17: Office Supplies | C17: 34592.1 | D17: 15927.1 | F17: =B17 -> Office Supplies | G17: =C17 -> 34592.1 | H17: =D17 -> 15927.1
B18: Grand Total | C18: 277676.56 | D18: 114401.56
B23: Order Date (Month) | C23: Sum of Net Sales | D23: Sum of Profit
B24: Jan | C24: 18719.1 | D24: 7379.1
B25: Feb | C25: 20586.15 | D25: 9251.15
B26: Mar | C26: 20480.25 | D26: 8560.25
B27: Apr | C27: 28154.9 | D27: 9634.9
B28: May | C28: 47321.05 | D28: 19416.05
B29: Jun | C29: 18673.95 | D29: 8333.95
B30: Jul | C30: 31764.25 | D30: 13569.25
B31: Aug | C31: 31500.65 | D31: 12340.65
B32: Sep | C32: 13200.88 | D32: 5580.88
B33: Oct | C33: 23309.98 | D33: 10049.98
B34: Nov | C34: 10717.3 | D34: 5057.3
B35: Dec | C35: 13248.1 | D35: 5228.1
B36: Grand Total | C36: 277676.56 | D36: 114401.56
B40: Row Labels | C40: Count of Order ID
B41: Cancelled | C41: 0.19
B42: Completed | C42: 0.6
B43: Returned | C43: 0.21
B44: Grand Total | C44: 1
C50: Avg. Satisfaction Score | D50: =AVERAGEIF(TransactionsTable[Order Status],"Completed",TransactionsTable[Satisfaction Score]) -> 2.8833333
B53: 0 | C53: Value | D53: =D50*20 -> 57.666667
B54: 0.25 | C54: Pointer | D54: 2
B55: 0.5 | D55: =200-D53-D54 -> 140.33333
B56: 0.25
B57: 1

Sheet Products
A1: Product ID | B1: Product Name | C1: Category | D1: Unit Cost | E1: List Price
A2: PROD-001 | B2: Bluetooth Speaker | C2: Electronics | D2: 950 | E2: 1650
A3: PROD-002 | B3: Wireless Mouse | C3: Electronics | D3: 310 | E3: 620
A4: PROD-003 | B4: USB-C Hub | C4: Electronics | D4: 850 | E4: 1450
A5: PROD-004 | B5: Webcam | C5: Electronics | D5: 700 | E5: 1250
A6: PROD-005 | B6: Notebook Pack | C6: Office Supplies | D6: 80 | E6: 150
A7: PROD-006 | B7: Pen Set | C7: Office Supplies | D7: 45 | E7: 90
A8: PROD-007 | B8: Desk Organizer | C8: Office Supplies | D8: 180 | E8: 340
A9: PROD-008 | B9: Printer Paper | C9: Office Supplies | D9: 210 | E9: 380
A10: PROD-009 | B10: Coffee Mug | C10: Home | D10: 90 | E10: 170
A11: PROD-010 | B11: LED Desk Lamp | C11: Home | D11: 420 | E11: 760
A12: PROD-011 | B12: Storage Box | C12: Home | D12: 130 | E12: 260
A13: PROD-012 | B13: Water Bottle | C13: Home | D13: 160 | E13: 300
... A16: PROD-015 | B16: Hoodie | C16: Apparel | D16: 450 | E16: 900
